[
    {
      "name": "Bisbee Pride",
      "date": "2023-06-18"
    },{
      "name": "Baltimore Pride",
      "date": "2023-06-19"
    },{
      "name": "Whitman in Love",
      "date": "2023-06-21"
    },{
      "name": "Milan Pride",
      "date": "2023-06-22"
    },{
      "name": "Brutally Proud",
      "date": "2023-06-23"
    },{
      "name": "Anadalucia Proud",
      "date": "2023-06-24"
    },{
      "name": "Allegra Pride",
      "date": "2023-06-25"
    },{
      "name": "Helsinki Pride",
      "date": "2023-06-26"
    },{
      "name": "Luxembourg Pride",
      "date": "2023-07-01"
    },{
      "name": "San Diego Pride",
      "date": "2023-07-08"
    },{
      "name": "Isle of Wight Pride",
      "date": "2023-07-14"
    },{
      "name": "Croydon Pride",
      "date": "2023-07-15"
    },{
      "name": "Berlin Pride Week",
      "date": "2023-07-19"
    },{
      "name": "Manuel Antonio Pride",
      "date": "2023-07-22"
    },{
      "name": "Hamburg Pride",
      "date": "2023-07-29"
    },{
      "name": "Cork LGBT Pride Festival",
      "date": "2023-07-30"
    },{
      "name": "Stockholm Pride",
      "date": "2023-07-31"
    },{
      "name": "Amsterdam Pride 2023",
      "date": "2023-08-01"
    },{
      "name": "Montreal LGBTQ Pride",
      "date": "2023-08-03"
    }
  ]
  